serialzy/__init__.py
serialzy/api.py
serialzy/base.py
serialzy/cloudpickle.py
serialzy/errors.py
serialzy/exception.py
serialzy/registry.py
serialzy/types.py
serialzy/utils.py
serialzy/version.py
serialzy/serializers/__init__.py
serialzy/serializers/base_model.py
serialzy/serializers/catboost.py
serialzy/serializers/ellipsis.py
serialzy/serializers/lightgbm.py
serialzy/serializers/onnx.py
serialzy/serializers/primitive.py
serialzy/serializers/proto.py
serialzy/serializers/sequence.py
serialzy/serializers/sklearn.py
serialzy/serializers/tensorflow.py
serialzy/serializers/torch.py
serialzy/serializers/union.py
serialzy/serializers/xgboost.py
serialzy/version/version
serialzy-1.5.2.dist-info/AUTHORS
serialzy-1.5.2.dist-info/LICENSE
serialzy-1.5.2.dist-info/METADATA
serialzy-1.5.2.dist-info/WHEEL
serialzy-1.5.2.dist-info/top_level.txt
serialzy-1.5.2.dist-info/RECORD
