Metadata-Version: 2.1
Name: serialzy
Version: 1.5.2
Author: ʎzy developers
License: LICENSE
Classifier: Programming Language :: Python :: 3.7
Classifier: Programming Language :: Python :: 3.8
Classifier: Programming Language :: Python :: 3.9
Classifier: Programming Language :: Python :: 3.10
Classifier: Programming Language :: Python :: 3.11
Requires-Python: >=3.7
License-File: LICENSE
License-File: AUTHORS
Requires-Dist: packaging >=21.3.0
Requires-Dist: typing-extensions >=4.4.0
